centricube_ragas/__init__.py
centricube_ragas/_analytics.py
centricube_ragas/_version.py
centricube_ragas/async_utils.py
centricube_ragas/evaluation.py
centricube_ragas/exceptions.py
centricube_ragas/utils.py
centricube_ragas/validation.py
centricube_ragas/embeddings/__init__.py
centricube_ragas/embeddings/base.py
centricube_ragas/langchain/__init__.py
centricube_ragas/langchain/evalchain.py
centricube_ragas/langsmith/__init__.py
centricube_ragas/langsmith/evaluator.py
centricube_ragas/llama_index/__init__.py
centricube_ragas/llama_index/evaluation.py
centricube_ragas/llms/__init__.py
centricube_ragas/llms/base.py
centricube_ragas/llms/langchain.py
centricube_ragas/llms/llamaindex.py
centricube_ragas/llms/openai.py
centricube_ragas/metrics/__init__.py
centricube_ragas/metrics/_answer_correctness.py
centricube_ragas/metrics/_answer_correctness_centricube.py
centricube_ragas/metrics/_answer_recall_centricube.py
centricube_ragas/metrics/_answer_relevance.py
centricube_ragas/metrics/_answer_similarity.py
centricube_ragas/metrics/_context_precision.py
centricube_ragas/metrics/_context_recall.py
centricube_ragas/metrics/_context_relevancy.py
centricube_ragas/metrics/_faithfulness.py
centricube_ragas/metrics/base.py
centricube_ragas/metrics/critique.py
centricube_ragas/testset/__init__.py
centricube_ragas/testset/prompts.py
centricube_ragas/testset/testset_generator.py
centricube_ragas/testset/utils.py
centricube_ragas/trainset/__init__.py
centricube_ragas/trainset/prompts.py
centricube_ragas/trainset/trainset_generator.py
centricube_ragas/trainset/utils.py
centricube_ragas-1.0.4.dist-info/METADATA
centricube_ragas-1.0.4.dist-info/WHEEL
centricube_ragas-1.0.4.dist-info/top_level.txt
centricube_ragas-1.0.4.dist-info/RECORD
