Metadata-Version: 2.4
Name: centricube_ragas
Version: 1.0.4
Summary: centricube ragas modules
Home-page: https://github.com/cicit/centricube
Author: CICIT
Author-email: jweelee@qq.com
License: Apache 2.0
Classifier: Programming Language :: Python :: 3
Classifier: Programming Language :: Python :: 3.6
Classifier: Programming Language :: Python :: 3.7
Classifier: Programming Language :: Python :: 3.8
Classifier: Programming Language :: Python :: 3.9
Classifier: License :: OSI Approved :: Apache Software License
Classifier: Operating System :: OS Independent
Requires-Python: >=3.6
Requires-Dist: langchain==0.3.*
Requires-Dist: datasets==2.19.1
Requires-Dist: setuptools==80.9.0
Requires-Dist: httpx==0.27.2
Requires-Dist: openai==1.*
Requires-Dist: dataclasses==0.6
Requires-Dist: tenacity==8.3.0
Requires-Dist: tqdm==4.67.1
Requires-Dist: numpy==1.26.4
Requires-Dist: pysbd==0.3.4
Requires-Dist: pandas==2.3.0
Requires-Dist: langsmith==0.4.1
Requires-Dist: pydantic
Requires-Dist: requests==2.31.0
Dynamic: author
Dynamic: author-email
Dynamic: classifier
Dynamic: description
Dynamic: description-content-type
Dynamic: home-page
Dynamic: license
Dynamic: requires-dist
Dynamic: requires-python
Dynamic: summary
